AUTHORS.rst
CONTRIBUTING.rst
HISTORY.rst
LICENSE
MANIFEST.in
README.rst
VERSION
setup.cfg
setup.py
docs/Makefile
docs/authors.rst
docs/conf.py
docs/contributing.rst
docs/history.rst
docs/index.rst
docs/installation.rst
docs/make.bat
docs/readme.rst
docs/usage.rst
markdown_manager/__init__.py
markdown_manager/cli.py
markdown_manager/markdown_manager.py
markdown_manager.egg-info/PKG-INFO
markdown_manager.egg-info/SOURCES.txt
markdown_manager.egg-info/dependency_links.txt
markdown_manager.egg-info/entry_points.txt
markdown_manager.egg-info/not-zip-safe
markdown_manager.egg-info/requires.txt
markdown_manager.egg-info/top_level.txt
requirements/prod.txt
requirements/test.txt
tests/__init__.py
tests/test_markdown_manager.py