Metadata-Version: 2.1
Name: markdown-manager
Version: 0.1.2
Summary: Small python utility for managing daily todos written in Markdown
Home-page: https://gitlab.com/paul_armstrong/markdown_manager
Author: Paul Armstrong
Author-email: parmstrong@gitlab.com
License: MIT license
Keywords: markdown_manager
Platform: UNKNOWN
Classifier: Development Status :: 2 - Pre-Alpha
Classifier: Intended Audience :: Developers
Classifier: License :: OSI Approved :: MIT License
Classifier: Natural Language :: English
Classifier: Programming Language :: Python :: 3
Classifier: Programming Language :: Python :: 3.6
Classifier: Programming Language :: Python :: 3.7
Classifier: Programming Language :: Python :: 3.8
Requires-Python: >=3.6
License-File: LICENSE
License-File: AUTHORS.rst
